nlprov/__init__.py
nlprov/preprocessing.py
nlprov/similarity_calc.py
nlprov/vectorize.py
nlprov/test/__init__.py
nlprov/test/test_preprocess.py
nlprov/test/test_similarity_calc.py
nlprov/test/test_vectorize.py
nlprov-1.1.0.dist-info/LICENSE.txt
nlprov-1.1.0.dist-info/METADATA
nlprov-1.1.0.dist-info/WHEEL
nlprov-1.1.0.dist-info/top_level.txt
nlprov-1.1.0.dist-info/RECORD
