Metadata-Version: 2.1
Name: nlprov
Version: 1.1.0
Summary: A Python package for common Natural Language Processing tasks
Home-page: https://github.com/johnsonandjohnson/nlprov
Author: Johnson & Johnson HTC Advanced Analytics
Classifier: Development Status :: 5 - Production/Stable
Classifier: License :: OSI Approved :: MIT License
Classifier: Intended Audience :: Developers
Classifier: Intended Audience :: Education
Classifier: Intended Audience :: Healthcare Industry
Classifier: Intended Audience :: Information Technology
Classifier: Programming Language :: Python :: 3.7
Classifier: Topic :: Scientific/Engineering
Requires-Python: >=3.7
License-File: LICENSE.txt
Requires-Dist: pandas (>=1.0.0)
Requires-Dist: spacy (>=3.4)
Requires-Dist: nltk (>=3.4.3)
Requires-Dist: langid (>=1.1.6)
Requires-Dist: scikit-learn (>=0.21.3)
